treecontainers/__init__.py
treecontainers/prioritymap.py
treecontainers-0.0.1.dist-info/LICENSE.txt
treecontainers-0.0.1.dist-info/METADATA
treecontainers-0.0.1.dist-info/WHEEL
treecontainers-0.0.1.dist-info/top_level.txt
treecontainers-0.0.1.dist-info/RECORD
