Metadata-Version: 2.1
Name: treecontainers
Version: 0.0.1
Summary: Tree Containers -- PriorityMap, PrioritySet, TreeMap
Home-page: UNKNOWN
Author: Ryan Tjoa
License: Apache 2.0
Platform: UNKNOWN
Classifier: Intended Audience :: Developers
Classifier: License :: OSI Approved :: Apache Software License
Classifier: Natural Language :: English
Classifier: Programming Language :: Python :: 3
Classifier: Operating System :: OS Independent
License-File: LICENSE.txt
